kickscore/__init__.py
kickscore/fitter/__init__.py
kickscore/fitter/batch.py
kickscore/fitter/fitter.py
kickscore/fitter/recursive.py
kickscore/item.py
kickscore/kernel/__init__.py
kickscore/kernel/affine.py
kickscore/kernel/constant.py
kickscore/kernel/exponential.py
kickscore/kernel/kernel.py
kickscore/kernel/matern32.py
kickscore/kernel/matern52.py
kickscore/kernel/periodic.py
kickscore/kernel/wiener.py
kickscore/model.py
kickscore/observation/__init__.py
kickscore/observation/gaussian.py
kickscore/observation/observation.py
kickscore/observation/ordinal.py
kickscore/observation/poisson.py
kickscore/observation/utils.py
kickscore/plotting.py
kickscore/py.typed
kickscore-0.2.0.dist-info/licenses/LICENSE
kickscore-0.2.0.dist-info/WHEEL
kickscore-0.2.0.dist-info/METADATA
kickscore-0.2.0.dist-info/RECORD
