Metadata-Version: 2.4
Name: kickscore
Version: 0.2.0
Summary: A dynamic skill rating system.
Keywords: elo,ranking,skill,score,rating,strength,game,comparison,match
Author: Lucas Maystre
Author-email: Lucas Maystre <lucas@maystre.ch>
License-Expression: MIT
License-File: LICENSE
Classifier: Development Status :: 4 - Beta
Classifier: License :: OSI Approved :: MIT License
Classifier: Intended Audience :: Science/Research
Classifier: Topic :: Scientific/Engineering :: Mathematics
Classifier: Topic :: Scientific/Engineering :: Artificial Intelligence
Classifier: Topic :: Games/Entertainment
Classifier: Programming Language :: Python :: 3
Requires-Dist: numpy
Requires-Dist: scipy
Requires-Dist: numba
Requires-Dist: matplotlib ; extra == 'all'
Requires-Dist: notebook ; extra == 'all'
Requires-Python: >=3.10
Project-URL: Homepage, https://github.com/lucasmaystre/kickscore
Project-URL: Issues, https://github.com/lucasmaystre/kickscore/issues
Project-URL: Repository, https://github.com/lucasmaystre/kickscore.git
Provides-Extra: all
